win_cat/__init__.py
win_cat/cat.py
win_cat-0.2.0.dist-info/LICENSE
win_cat-0.2.0.dist-info/METADATA
win_cat-0.2.0.dist-info/WHEEL
win_cat-0.2.0.dist-info/entry_points.txt
win_cat-0.2.0.dist-info/top_level.txt
win_cat-0.2.0.dist-info/RECORD
